veles/__init__.py
veles_vh-0.1.1.dist-info/LICENSE
veles_vh-0.1.1.dist-info/METADATA
veles_vh-0.1.1.dist-info/WHEEL
veles_vh-0.1.1.dist-info/top_level.txt
veles_vh-0.1.1.dist-info/RECORD
